tinypl/__init__.py
tinypl/dataloader.py
tinypl/debug.py
tinypl/filter.py
tinypl/flatten.py
tinypl/item.py
tinypl/map.py
tinypl/marker.py
tinypl/order.py
tinypl/partition.py
tinypl/pipe.py
tinypl/process.py
tinypl/ratelimit.py
tinypl/thread.py
tinypl/util.py
tinypl-0.1.0.dist-info/LICENSE
tinypl-0.1.0.dist-info/METADATA
tinypl-0.1.0.dist-info/WHEEL
tinypl-0.1.0.dist-info/top_level.txt
tinypl-0.1.0.dist-info/RECORD
