Metadata-Version: 2.1
Name: tinypl
Version: 0.1.0
Summary: Pipelines for asynchronous processing
Home-page: https://github.com/fferflo/tinypl
Author: Florian Fervers
Author-email: florian.fervers@gmail.com
License: MIT
License-File: LICENSE
Requires-Dist: pytest
Requires-Dist: threadpoolctl
